librecubo_download/__init__.py
librecubo_download/main.py
librecubo_download/utils.py
librecubo_download-0.0.2.dist-info/LICENSE
librecubo_download-0.0.2.dist-info/METADATA
librecubo_download-0.0.2.dist-info/WHEEL
librecubo_download-0.0.2.dist-info/RECORD
