Metadata-Version: 2.1
Name: librecubo_download
Version: 0.0.2
Summary: This is a template repository for Python projects that use Poetry for their dependency management.
Home-page: https://github.com/jfphlorecti/librecubo-download
Author: Jair Flores
Author-email: fjfphlorecti@gmail.com
Requires-Python: >=3.9,<4.0
Classifier: Programming Language :: Python :: 3
Classifier: Programming Language :: Python :: 3.9
Classifier: Programming Language :: Python :: 3.10
Classifier: Programming Language :: Python :: 3.11
Classifier: Programming Language :: Python :: 3.12
Requires-Dist: cubo (>=2023.7.2,<2024.0.0)
Project-URL: Documentation, https://jfphlorecti.github.io/librecubo-download/
Project-URL: Repository, https://github.com/jfphlorecti/librecubo-download
